csmlog/__init__.py
csmlog/google_sheets_handler.py
csmlog/system_call.py
csmlog/udp_handler.py
csmlog/udp_handler_receiver.py
csmlog-0.28.0.dist-info/METADATA
csmlog-0.28.0.dist-info/WHEEL
csmlog-0.28.0.dist-info/entry_points.txt
csmlog-0.28.0.dist-info/top_level.txt
csmlog-0.28.0.dist-info/RECORD
