Metadata-Version: 2.1
Name: csmlog
Version: 0.28.0
Home-page: http://github.com/csm10495/csmlog
Author: csm10495
Author-email: csm10495@gmail.com
License: MIT License
Classifier: Intended Audience :: Developers
Classifier: Natural Language :: English
Classifier: Operating System :: Microsoft :: Windows
Classifier: Programming Language :: Python
Classifier: Programming Language :: Python :: 3
Requires-Python: >=3.6
Requires-Dist: six
Requires-Dist: gspread <6.0.0
